waketfup/__init__.py
waketfup/main.py
waketfup/utils/__init__.py
waketfup-2.0.0.dist-info/METADATA
waketfup-2.0.0.dist-info/WHEEL
waketfup-2.0.0.dist-info/entry_points.txt
waketfup-2.0.0.dist-info/RECORD
