Metadata-Version: 2.4
Name: waketfup
Version: 2.0.0
Summary: Keep windows away from sleeping
Author: Milton Chow
Requires-Python: >=3.8,<4.0
Classifier: Programming Language :: Python :: 3
Classifier: Programming Language :: Python :: 3.8
Classifier: Programming Language :: Python :: 3.9
Classifier: Programming Language :: Python :: 3.10
Classifier: Programming Language :: Python :: 3.11
Classifier: Programming Language :: Python :: 3.12
Classifier: Programming Language :: Python :: 3.13
Classifier: Programming Language :: Python :: 3.14
Requires-Dist: datetime (>=5.5,<6.0)
Requires-Dist: pyautogui (>=0.9.54,<0.10.0)
